<?xml version="1.0" encoding="utf-8"?>
<text author="Guardian staff reporter" categories="World news" date="2013-10-02" description="Silvio Berlusconi pledges to support the country's coalition government, despite having previously threatened to withdraw his MPs" fingerprint="5f9acb5793a2caad" hostname="theguardian.com" sitename="The Guardian" tags="Silvio Berlusconi,Italy,Europe,World news,Enrico Letta" title="Silvio Berlusconi backs Italy's coalition government in u-turn - video" url="http://www.theguardian.com/world/video/2013/oct/02/silvio-berlusconi-italy-coalition-government-video">
<main>
<head rend="h1">Silvio Berlusconi backs Italy's coalition government in u-turn - video</head>
<p>This article is more than 11 years old</p>
<p>Silvio Berlusconi, leader of Italy's centre-right Freedom People (PdL) party, pledges to support the country's coalition government, despite having previously threatened to withdraw his MPs. The 77-year-old former prime minister, who was convicted of tax fraud in August, said his party would vote to support prime minister Enrico Letta's coalition. The u-turn came after senior PdL members refused to bring down the government at Berlusconi's behest</p>
</main>
<comments/>
</text>